gitmanager/__init__.py
gitmanager/github.py
gitmanager/handler.py
gitmanager/utils.py
gitmantool-0.7.dist-info/LICENSE
gitmantool-0.7.dist-info/METADATA
gitmantool-0.7.dist-info/WHEEL
gitmantool-0.7.dist-info/entry_points.txt
gitmantool-0.7.dist-info/top_level.txt
gitmantool-0.7.dist-info/RECORD
