Metadata-Version: 2.1
Name: gitmantool
Version: 0.7
Summary: Console tool for manage projects on github/gitlab
Home-page: https://github.com/katmai1/gitmanager
Author: katmai
Author-email: katmai.mobil@gmail.com
License: UNKNOWN
Platform: UNKNOWN
Classifier: Programming Language :: Python :: 3
Requires-Python: >=3.6
Requires-Dist: docopt
Requires-Dist: pygithub
Requires-Dist: gitlab
Requires-Dist: pyyaml
Requires-Dist: colorama
